[
 {
  "docstatus": 0,
  "doctype": "Journal Type",
  "journal_type": "Internal",
  "journal_weight": 1,
  "modified": "2024-07-04 05:31:55.143496",
  "name": "Internal"
 },
 {
  "docstatus": 0,
  "doctype": "Journal Type",
  "journal_type": "Indexed",
  "journal_weight": 2,
  "modified": "2024-07-04 05:32:07.754719",
  "name": "Indexed"
 },
 {
  "docstatus": 0,
  "doctype": "Journal Type",
  "journal_type": "Q4",
  "journal_weight": 3,
  "modified": "2024-07-04 05:35:49.330215",
  "name": "Q4"
 },
 {
  "docstatus": 0,
  "doctype": "Journal Type",
  "journal_type": "Q3",
  "journal_weight": 4,
  "modified": "2024-07-04 05:36:00.429149",
  "name": "Q3"
 },
 {
  "docstatus": 0,
  "doctype": "Journal Type",
  "journal_type": "Q2",
  "journal_weight": 5,
  "modified": "2024-07-04 05:36:22.017345",
  "name": "Q2"
 },
 {
  "docstatus": 0,
  "doctype": "Journal Type",
  "journal_type": "Q1",
  "journal_weight": 6,
  "modified": "2024-07-04 05:36:35.040096",
  "name": "Q1"
 }
]